{
  "criteria": {
    "obtain_tardis": {
      "trigger": "tardis:obtain_tardis"
    },
    "quantiscope_iron": {
      "trigger": "minecraft:inventory_changed",
      "conditions": {
        "items": [
          {
            "item": "tardis:quantiscope_iron"
          }
        ]
      }
    },
    "quantiscope_brass": {
      "trigger": "minecraft:inventory_changed",
      "conditions": {
        "items": [
          {
            "item": "tardis:quantiscope_brass"
          }
        ]
      }
    }
  },
  "requirements": [
    ["quantiscope_brass", "quantiscope_iron"],
    ["nav_com"],
    ["obtain_tardis"]
  ]
}